MANIFEST.in
currency.py
setup.py
Currency.egg-info/PKG-INFO
Currency.egg-info/SOURCES.txt
Currency.egg-info/dependency_links.txt
Currency.egg-info/not-zip-safe
Currency.egg-info/top_level.txt