Metadata-Version: 1.0
Name: Currency
Version: 0.1.2
Summary: Currency conversion using openexangerates API
Home-page: UNKNOWN
Author: Roberto Gea
Author-email: rogeaa.cyc@gmail.com
License: MIT
Download-URL: https://bitbucket.org/alquimista/currency/downloads
Keywords: currency open exange rates
Platform: UNKNOWN
Classifier: Development Status :: 4 - Beta
Classifier: Environment :: Console
Classifier: Environment :: Other Environment
Classifier: Intended Audience :: Developers
Classifier: Intended Audience :: Financial and Insurance Industry
Classifier: License :: OSI Approved :: MIT License
Classifier: Natural Language :: English
Classifier: Operating System :: Microsoft :: Windows
Classifier: Operating System :: POSIX :: Linux
Classifier: Operating System :: MacOS
Classifier: Programming Language :: Python :: 2.7
Classifier: Programming Language :: Python :: 3
Classifier: Topic :: Software Development :: Libraries
